keyta/IProcess.py
keyta/Listener.py
keyta/__init__.py
keyta/__main__.py
keyta/app.py
keyta/icon.png
keyta/manage.py
keyta/rf_remote_server.py
keyta/DE/__init__.py
keyta/DE/__main__.py
keyta/apps/__init__.py
keyta/apps/actions/__init__.py
keyta/apps/actions/apps.py
keyta/apps/actions/views.py
keyta/apps/actions/admin/__init__.py
keyta/apps/actions/admin/action.py
keyta/apps/actions/admin/execution.py
keyta/apps/actions/admin/library_import.py
keyta/apps/actions/admin/robot_keywordcall.py
keyta/apps/actions/admin/steps_inline.py
keyta/apps/actions/migrations/0001_initial.py
keyta/apps/actions/migrations/0002_alter_action_options_and_more.py
keyta/apps/actions/migrations/0003_windowaction.py
keyta/apps/actions/migrations/__init__.py
keyta/apps/actions/models/__init__.py
keyta/apps/actions/models/action.py
keyta/apps/actions/models/execution.py
keyta/apps/actions/models/library_import.py
keyta/apps/actions/models/robot_keywordcall.py
keyta/apps/actions/tests/__init__.py
keyta/apps/common/__init__.py
keyta/apps/common/abc.py
keyta/apps/common/widgets.py
keyta/apps/common/admin/__init__.py
keyta/apps/common/admin/base_admin.py
keyta/apps/common/admin/base_inline.py
keyta/apps/common/forms/__init__.py
keyta/apps/common/forms/baseform.py
keyta/apps/common/forms/optional_argument.py
keyta/apps/executions/__init__.py
keyta/apps/executions/apps.py
keyta/apps/executions/errors.py
keyta/apps/executions/tests.py
keyta/apps/executions/views.py
keyta/apps/executions/admin/__init__.py
keyta/apps/executions/admin/execution.py
keyta/apps/executions/admin/execution_inline.py
keyta/apps/executions/admin/keyword_execution.py
keyta/apps/executions/admin/keyword_execution_call.py
keyta/apps/executions/admin/keyword_execution_inline.py
keyta/apps/executions/admin/keyword_execution_setup.py
keyta/apps/executions/admin/keyword_execution_setup_inline.py
keyta/apps/executions/admin/library_import_inline.py
keyta/apps/executions/admin/resource_imports_inline.py
robotframework_keyta-1.2.3.dist-info/entry_points.txt
robotframework_keyta-1.2.3.dist-info/licenses/LICENSE
robotframework_keyta-1.2.3.dist-info/WHEEL
robotframework_keyta-1.2.3.dist-info/METADATA
robotframework_keyta-1.2.3.dist-info/RECORD
