Metadata-Version: 2.4
Name: robotframework-keyta
Version: 1.2.3
Summary: A web UI for Robot Framework
Author-email: "Marduk Bolanos, imbus Rheinland" <testautomatisierung@imbus.de>
Requires-Python: >=3.10
Classifier: Development Status :: 5 - Production/Stable
Classifier: License :: OSI Approved :: Apache Software License
Classifier: Operating System :: Microsoft :: Windows :: Windows 10
Classifier: Programming Language :: Python
Classifier: Programming Language :: Python :: 3
Classifier: Programming Language :: Python :: 3.10
Classifier: Programming Language :: Python :: 3.11
Classifier: Programming Language :: Python :: 3.12
Classifier: Programming Language :: Python :: 3.13
Classifier: Topic :: Software Development :: Testing
License-File: LICENSE
Requires-Dist: django~=5.2.0
Requires-Dist: django-admin-sortable2==2.2.3
Requires-Dist: django-jazzmin~=3.0
Requires-Dist: django-select2~=8.2
Requires-Dist: django-tinymce~=4.1
Requires-Dist: Jinja2~=3.1
Requires-Dist: pystray~=0.19
Requires-Dist: robotframework>=7
Project-URL: Homepage, https://pypi.org/project/robotframework-keyta/
Project-URL: Repository, https://github.com/RF-KeyTA/KeyTA.git
